turbolightdi/__init__.py
turbolightdi/container.py
turbolightdi/decorators.py
turbolightdi/exceptions.py
turbolightdi/scanner.py
turbolightdi-0.1.1.dist-info/METADATA
turbolightdi-0.1.1.dist-info/WHEEL
turbolightdi-0.1.1.dist-info/licenses/LICENSE
turbolightdi-0.1.1.dist-info/RECORD
