Metadata-Version: 2.4
Name: turbolightdi
Version: 0.1.1
Summary: TurboLightDI is a lightweight, high-performance Inversion of Control (IoC) container.
Project-URL: Homepage, https://github.com/turborg/turbolightdi
Project-URL: Repository, https://github.com/turborg/turbolightdi
Project-URL: Bug Tracker, https://github.com/turborg/turbolightdi/issues
Author-email: stefanzc <stefanzc@turborg.com>
License: MIT
License-File: LICENSE
Keywords: dependency-injection,fast,high-performance,inversion-of-control,micro-di,minimalist,turborg
Classifier: Development Status :: 3 - Alpha
Classifier: Framework :: AsyncIO
Classifier: Framework :: Pytest
Classifier: Intended Audience :: Developers
Classifier: License :: OSI Approved :: MIT License
Classifier: Operating System :: OS Independent
Classifier: Programming Language :: Python
Classifier: Programming Language :: Python :: 3
Classifier: Programming Language :: Python :: 3 :: Only
Classifier: Programming Language :: Python :: 3.10
Classifier: Programming Language :: Python :: 3.11
Classifier: Programming Language :: Python :: 3.12
Classifier: Programming Language :: Python :: 3.13
Classifier: Programming Language :: Python :: 3.14
Classifier: Programming Language :: Python :: Implementation :: CPython
Classifier: Programming Language :: Python :: Implementation :: PyPy
Classifier: Topic :: Software Development
Classifier: Topic :: Software Development :: Libraries
Classifier: Topic :: Software Development :: Libraries :: Python Modules
Provides-Extra: dev
Requires-Dist: mypy; extra == 'dev'
Requires-Dist: pre-commit; extra == 'dev'
Requires-Dist: pytest; extra == 'dev'
Requires-Dist: pytest-asyncio; extra == 'dev'
Requires-Dist: ruff; extra == 'dev'
